WordTransformer/InputExample.py
WordTransformer/WordTransformer.py
WordTransformer/__init__.py
wordtransformer_languagechange-0.0.1.dist-info/METADATA
wordtransformer_languagechange-0.0.1.dist-info/WHEEL
wordtransformer_languagechange-0.0.1.dist-info/top_level.txt
wordtransformer_languagechange-0.0.1.dist-info/RECORD
