Metadata-Version: 2.4
Name: WordTransformer-LanguageChange
Version: 0.0.1
Summary: WiC Pretrained Model for Cross-Lingual LEXical sEMantic changE
Home-page: https://github.com/pierluigic/xl-lexeme
Author: Pierluigi Cassotti
Platform: all
Classifier: Programming Language :: Python :: 3
Classifier: License :: OSI Approved :: MIT License
Classifier: Operating System :: OS Independent
Requires-Python: >=3.8
Requires-Dist: sentence-transformers
Dynamic: author
Dynamic: classifier
Dynamic: description-content-type
Dynamic: home-page
Dynamic: platform
Dynamic: requires-dist
Dynamic: requires-python
Dynamic: summary
